Workbook

Sheet PRODUCTOS
A1: Producto | B1: Precio | C1: Costo | D1: Ganancia
D2: =B2-C2 -> 0
D3: =B3-C3 -> 0
D4: =B4-C4 -> 0
D5: =B5-C5 -> 0
D6: =B6-C6 -> 0
D7: =B7-C7 -> 0
D8: =B8-C8 -> 0
D9: =B9-C9 -> 0
D10: =B10-C10 -> 0
D11: =B11-C11 -> 0
D12: =B12-C12 -> 0
D13: =B13-C13 -> 0
... D101: =B101-C101 -> 0

Sheet INSUMOS
A1: Insumo | B1: Stock Inicial | C1: Compras | D1: Consumo | E1: Stock Actual
D2: =SUMPRODUCT(('RECETAS'!B2:B100=A2)*'RECETAS'!C2:C100*(SUMIF(VENTAS!B2:B1000,'RECETAS'!A2:A100,VENTAS!C2:C1000))) -> 0 | E2: =B2+C2-D2 -> 0
D3: =SUMPRODUCT(('RECETAS'!B3:B101=A3)*'RECETAS'!C3:C101*(SUMIF(VENTAS!B3:B1001,'RECETAS'!A3:A101,VENTAS!C3:C1001))) -> 0 | E3: =B3+C3-D3 -> 0
D4: =SUMPRODUCT(('RECETAS'!B4:B102=A4)*'RECETAS'!C4:C102*(SUMIF(VENTAS!B4:B1002,'RECETAS'!A4:A102,VENTAS!C4:C1002))) -> 0 | E4: =B4+C4-D4 -> 0
D5: =SUMPRODUCT(('RECETAS'!B5:B103=A5)*'RECETAS'!C5:C103*(SUMIF(VENTAS!B5:B1003,'RECETAS'!A5:A103,VENTAS!C5:C1003))) -> 0 | E5: =B5+C5-D5 -> 0
D6: =SUMPRODUCT(('RECETAS'!B6:B104=A6)*'RECETAS'!C6:C104*(SUMIF(VENTAS!B6:B1004,'RECETAS'!A6:A104,VENTAS!C6:C1004))) -> 0 | E6: =B6+C6-D6 -> 0
D7: =SUMPRODUCT(('RECETAS'!B7:B105=A7)*'RECETAS'!C7:C105*(SUMIF(VENTAS!B7:B1005,'RECETAS'!A7:A105,VENTAS!C7:C1005))) -> 0 | E7: =B7+C7-D7 -> 0
D8: =SUMPRODUCT(('RECETAS'!B8:B106=A8)*'RECETAS'!C8:C106*(SUMIF(VENTAS!B8:B1006,'RECETAS'!A8:A106,VENTAS!C8:C1006))) -> 0 | E8: =B8+C8-D8 -> 0
D9: =SUMPRODUCT(('RECETAS'!B9:B107=A9)*'RECETAS'!C9:C107*(SUMIF(VENTAS!B9:B1007,'RECETAS'!A9:A107,VENTAS!C9:C1007))) -> 0 | E9: =B9+C9-D9 -> 0
D10: =SUMPRODUCT(('RECETAS'!B10:B108=A10)*'RECETAS'!C10:C108*(SUMIF(VENTAS!B10:B1008,'RECETAS'!A10:A108,VENTAS!C10:C1008))) -> 0 | E10: =B10+C10-D10 -> 0
D11: =SUMPRODUCT(('RECETAS'!B11:B109=A11)*'RECETAS'!C11:C109*(SUMIF(VENTAS!B11:B1009,'RECETAS'!A11:A109,VENTAS!C11:C1009))) -> 0 | E11: =B11+C11-D11 -> 0
D12: =SUMPRODUCT(('RECETAS'!B12:B110=A12)*'RECETAS'!C12:C110*(SUMIF(VENTAS!B12:B1010,'RECETAS'!A12:A110,VENTAS!C12:C1010))) -> 0 | E12: =B12+C12-D12 -> 0
D13: =SUMPRODUCT(('RECETAS'!B13:B111=A13)*'RECETAS'!C13:C111*(SUMIF(VENTAS!B13:B1011,'RECETAS'!A13:A111,VENTAS!C13:C1011))) -> 0 | E13: =B13+C13-D13 -> 0
... D101: =SUMPRODUCT(('RECETAS'!B101:B199=A101)*'RECETAS'!C101:C199*(SUMIF(VENTAS!B101:B1099,'RECETAS'!A101:A199,VENTAS!C101:C1099))) -> 0 | E101: =B101+C101-D101 -> 0

Sheet RECETAS
A1: Producto | B1: Insumo | C1: Cantidad

Sheet VENTAS
A1: Fecha | B1: Producto | C1: Cantidad | D1: Precio | E1: Total | F1: Mes
E2: =C2*D2 -> 0 | F2: =IF(A2="","",TEXT(A2,"yyyy-mm"))
E3: =C3*D3 -> 0 | F3: =IF(A3="","",TEXT(A3,"yyyy-mm"))
E4: =C4*D4 -> 0 | F4: =IF(A4="","",TEXT(A4,"yyyy-mm"))
D5: =IFERROR(VLOOKUP(B5,PRODUCTOS!A:B,2,FALSE),"") | E5: =C5*D5 -> #VALUE! | F5: =IF(A5="","",TEXT(A5,"yyyy-mm"))
D6: =IFERROR(VLOOKUP(B6,PRODUCTOS!A:B,2,FALSE),"") | E6: =C6*D6 -> #VALUE! | F6: =IF(A6="","",TEXT(A6,"yyyy-mm"))
D7: =IFERROR(VLOOKUP(B7,PRODUCTOS!A:B,2,FALSE),"") | E7: =C7*D7 -> #VALUE! | F7: =IF(A7="","",TEXT(A7,"yyyy-mm"))
D8: =IFERROR(VLOOKUP(B8,PRODUCTOS!A:B,2,FALSE),"") | E8: =C8*D8 -> #VALUE! | F8: =IF(A8="","",TEXT(A8,"yyyy-mm"))
D9: =IFERROR(VLOOKUP(B9,PRODUCTOS!A:B,2,FALSE),"") | E9: =C9*D9 -> #VALUE! | F9: =IF(A9="","",TEXT(A9,"yyyy-mm"))
D10: =IFERROR(VLOOKUP(B10,PRODUCTOS!A:B,2,FALSE),"") | E10: =C10*D10 -> #VALUE! | F10: =IF(A10="","",TEXT(A10,"yyyy-mm"))
D11: =IFERROR(VLOOKUP(B11,PRODUCTOS!A:B,2,FALSE),"") | E11: =C11*D11 -> #VALUE! | F11: =IF(A11="","",TEXT(A11,"yyyy-mm"))
D12: =IFERROR(VLOOKUP(B12,PRODUCTOS!A:B,2,FALSE),"") | E12: =C12*D12 -> #VALUE! | F12: =IF(A12="","",TEXT(A12,"yyyy-mm"))
D13: =IFERROR(VLOOKUP(B13,PRODUCTOS!A:B,2,FALSE),"") | E13: =C13*D13 -> #VALUE! | F13: =IF(A13="","",TEXT(A13,"yyyy-mm"))
D14: =IFERROR(VLOOKUP(B14,PRODUCTOS!A:B,2,FALSE),"") | E14: =C14*D14 -> #VALUE! | F14: =IF(A14="","",TEXT(A14,"yyyy-mm"))
D15: =IFERROR(VLOOKUP(B15,PRODUCTOS!A:B,2,FALSE),"") | E15: =C15*D15 -> #VALUE! | F15: =IF(A15="","",TEXT(A15,"yyyy-mm"))
D16: =IFERROR(VLOOKUP(B16,PRODUCTOS!A:B,2,FALSE),"") | E16: =C16*D16 -> #VALUE! | F16: =IF(A16="","",TEXT(A16,"yyyy-mm"))
... D1001: =IFERROR(VLOOKUP(B1001,PRODUCTOS!A:B,2,FALSE),"") | E1001: =C1001*D1001 -> #VALUE! | F1001: =IF(A1001="","",TEXT(A1001,"yyyy-mm"))

Sheet RESUMEN
A1: Mes | B1: Ventas | C1: Costos | D1: Ganancia
A2: 2026-01 | B2: =SUMIF(VENTAS!F:F,A2,VENTAS!E:E) -> 0 | C2: =SUMPRODUCT((VENTAS!F2:F1000=A2) *(VENTAS!C2:C1000) *IFERROR(VLOOKUP(VENTAS!B2:B1000,PRODUCTOS!A:C,3,FALSE),0)) -> 0 | D2: =B2-C2 -> 0
A3: 2026-02 | B3: =SUMIF(VENTAS!F:F,A3,VENTAS!E:E) -> 0 | C3: =SUMPRODUCT((VENTAS!F3:F1001=A3) *(VENTAS!C3:C1001) *IFERROR(VLOOKUP(VENTAS!B3:B1001,PRODUCTOS!A:C,3,FALSE),0)) -> 0 | D3: =B3-C3 -> 0
A4: 2026-03 | B4: =SUMIF(VENTAS!F:F,A4,VENTAS!E:E) -> 0 | C4: =SUMPRODUCT((VENTAS!F4:F1002=A4) *(VENTAS!C4:C1002) *IFERROR(VLOOKUP(VENTAS!B4:B1002,PRODUCTOS!A:C,3,FALSE),0)) -> 0 | D4: =B4-C4 -> 0
A5: 2026-04 | B5: =SUMIF(VENTAS!F:F,A5,VENTAS!E:E) -> 0 | C5: =SUMPRODUCT((VENTAS!F5:F1003=A5) *(VENTAS!C5:C1003) *IFERROR(VLOOKUP(VENTAS!B5:B1003,PRODUCTOS!A:C,3,FALSE),0)) -> 0 | D5: =B5-C5 -> 0
A6: 2026-05 | B6: =SUMIF(VENTAS!F:F,A6,VENTAS!E:E) -> 0 | C6: =SUMPRODUCT((VENTAS!F6:F1004=A6) *(VENTAS!C6:C1004) *IFERROR(VLOOKUP(VENTAS!B6:B1004,PRODUCTOS!A:C,3,FALSE),0)) -> 0 | D6: =B6-C6 -> 0
A7: 2026-06 | B7: =SUMIF(VENTAS!F:F,A7,VENTAS!E:E) -> 0 | C7: =SUMPRODUCT((VENTAS!F7:F1005=A7) *(VENTAS!C7:C1005) *IFERROR(VLOOKUP(VENTAS!B7:B1005,PRODUCTOS!A:C,3,FALSE),0)) -> 0 | D7: =B7-C7 -> 0
A8: 2026-07 | B8: =SUMIF(VENTAS!F:F,A8,VENTAS!E:E) -> 0 | C8: =SUMPRODUCT((VENTAS!F8:F1006=A8) *(VENTAS!C8:C1006) *IFERROR(VLOOKUP(VENTAS!B8:B1006,PRODUCTOS!A:C,3,FALSE),0)) -> 0 | D8: =B8-C8 -> 0
A9: 2026-08 | B9: =SUMIF(VENTAS!F:F,A9,VENTAS!E:E) -> 0 | C9: =SUMPRODUCT((VENTAS!F9:F1007=A9) *(VENTAS!C9:C1007) *IFERROR(VLOOKUP(VENTAS!B9:B1007,PRODUCTOS!A:C,3,FALSE),0)) -> 0 | D9: =B9-C9 -> 0
A10: 2026-09 | B10: =SUMIF(VENTAS!F:F,A10,VENTAS!E:E) -> 0 | C10: =SUMPRODUCT((VENTAS!F10:F1008=A10) *(VENTAS!C10:C1008) *IFERROR(VLOOKUP(VENTAS!B10:B1008,PRODUCTOS!A:C,3,FALSE),0)) -> 0 | D10: =B10-C10 -> 0
A11: 2026-10 | B11: =SUMIF(VENTAS!F:F,A11,VENTAS!E:E) -> 0 | C11: =SUMPRODUCT((VENTAS!F11:F1009=A11) *(VENTAS!C11:C1009) *IFERROR(VLOOKUP(VENTAS!B11:B1009,PRODUCTOS!A:C,3,FALSE),0)) -> 0 | D11: =B11-C11 -> 0
A12: 2026-11 | B12: =SUMIF(VENTAS!F:F,A12,VENTAS!E:E) -> 0 | C12: =SUMPRODUCT((VENTAS!F12:F1010=A12) *(VENTAS!C12:C1010) *IFERROR(VLOOKUP(VENTAS!B12:B1010,PRODUCTOS!A:C,3,FALSE),0)) -> 0 | D12: =B12-C12 -> 0
A13: 2026-12 | B13: =SUMIF(VENTAS!F:F,A13,VENTAS!E:E) -> 0 | C13: =SUMPRODUCT((VENTAS!F13:F1011=A13) *(VENTAS!C13:C1011) *IFERROR(VLOOKUP(VENTAS!B13:B1011,PRODUCTOS!A:C,3,FALSE),0)) -> 0 | D13: =B13-C13 -> 0
